{
  "vegg": "vegetarian",
  "chines": "chinese",
  "sinister13thurge@aol.com": "Sinister13thUrge@aol.com",
  "yuko": "Yuko",
  "christiana": "Christiana",
  "romona": "Romona",
  "freddy": "Freddy",
  "emely": "Emely",
  "will": "Will",
  "dcmilleraf@aol.com": "DCMillerAF@aol.com",
  "kylie": "Kylie",
  "adelle": "Adelle",
  "milan": "Milan",
  "keon": "Keon",
  "albert": "Albert",
  "kathern": "Kathern",
  "sheilah": "Sheilah",
  "marti": "Marti",
  "shelby": "Shelby",
  "tyrone": "Tyrone",
  "marissa": "Marissa",
  "colby": "Colby",
  "allyson": "Allyson",
  "veggie": "vegetarian",
  "rosaline": "Rosaline",
  "harry": "Harry",
  "ada": "Ada",
  "mj": "MJ"
}